pysptk/__init__.py
pysptk/_sptk.so
pysptk/conversion.py
pysptk/sptk.py
pysptk/synthesis.py
pysptk/util.py
pysptk-0.1.5.dist-info/DESCRIPTION.rst
pysptk-0.1.5.dist-info/METADATA
pysptk-0.1.5.dist-info/RECORD
pysptk-0.1.5.dist-info/WHEEL
pysptk-0.1.5.dist-info/metadata.json
pysptk-0.1.5.dist-info/top_level.txt
